octo_api/py.typed
octo_api/utils.py
octo_api/__init__.py
octo_api/products.py
octo_api/consumption.py
octo_api/api.py
octo_api/pagination.py
octo_api-0.1.1.dist-info/METADATA
octo_api-0.1.1.dist-info/LICENSE
octo_api-0.1.1.dist-info/top_level.txt
octo_api-0.1.1.dist-info/WHEEL
octo_api-0.1.1.dist-info/entry_points.txt
octo_api-0.1.1.dist-info/RECORD
