Metadata-Version: 2.1
Name: octo-api
Version: 0.1.1
Summary: Python interface to the Octopus Energy API.
Author-email: Dominic Davis-Foster <dominic@davis-foster.co.uk>
License: MIT
Home-page: https://github.com/domdfcoding/octo-api
Project-URL: Issue Tracker, https://github.com/domdfcoding/octo-api/issues
Project-URL: Source Code, https://github.com/domdfcoding/octo-api
Project-URL: Documentation, https://octo-api.readthedocs.io/en/latest
Platform: Windows
Platform: macOS
Platform: Linux
Classifier: Development Status :: 4 - Beta
Classifier: Intended Audience :: Developers
Classifier: License :: OSI Approved :: MIT License
Classifier: Operating System :: OS Independent
Classifier: Programming Language :: Python
Classifier: Programming Language :: Python :: 3 :: Only
Classifier: Programming Language :: Python :: 3.6
Classifier: Programming Language :: Python :: 3.7
Classifier: Programming Language :: Python :: 3.8
Classifier: Programming Language :: Python :: 3.9
Classifier: Programming Language :: Python :: Implementation :: CPython
Classifier: Topic :: Software Development :: Libraries :: Python Modules
Classifier: Typing :: Typed
Requires-Python: >=3.6
Requires-Dist: apeye>=0.3.0
Requires-Dist: attr-utils>=0.5.4
Requires-Dist: attrs>=20.2.0
Requires-Dist: backports-datetime-fromisoformat==1.0.0; python_version < "3.7"
Requires-Dist: domdf-python-tools>=1.5.0
Requires-Dist: enum-tools>=0.6.1
Requires-Dist: prettyprinter>=0.18.0
Requires-Dist: typing-extensions>=3.7.4.3
